{
  "scraping": {
    "headless": true,
    "timeout": 10000,
    "waitForSelector": 2000,
    "userAgent": "Mozilla/5.0 (Macintosh; Intel Mac OS X 10_15_7) AppleWebKit/537.36 (KHTML, like Gecko) Chrome/120.0.0.0 Safari/537.36",
    "viewport": {
      "width": 2560,
      "height": 1664
    }
  },
  "output": {
    "directory": "./output",
    "csvFilename": "scraped_data_{timestamp}.csv",
    "timestampFormat": "YYYY-MM-DD_HH-mm-ss"
  },
  "email": {
    "enabled": true,
    "smtp": {
      "host": "smtp.gmail.com",
      "port": 587,
      "secure": false
    },
    "auth": {},
    "from": "search-notifier@gmail.com",
    "to": [],
    "subject": "New Matches Found - {siteName}",
    "template": "default"
  },
  "changeDetection": {
    "enabled": true,
    "storageFile": "./data/change_history.json",
    "notifyOnChanges": ["price", "title", "description"]
  },
  "logging": {
    "level": "debug",
    "file": "./logs/scraper.log",
    "debug": {
      "enabled": true,
      "file": "./logs/debug.log",
      "mode": "overwrite",
      "displayPath": true
    }
  }
}
